devzery/__init__.py
devzery/core/__init__.py
devzery/core/base.py
devzery/django/__init__.py
devzery/django/middleware.py
devzery/flask/__init__.py
devzery/flask/middleware.py
devzery/requests/__init__.py
devzery/requests/interceptor.py
devzery/requests/patcher.py
devzery-0.1.0.dist-info/LICENSE
devzery-0.1.0.dist-info/METADATA
devzery-0.1.0.dist-info/WHEEL
devzery-0.1.0.dist-info/top_level.txt
devzery-0.1.0.dist-info/RECORD
